{
  "name":"FCMFCQ1K-startSavedState",
  "description" : "platform testing demo - FCMFCQ1K-startSavedState",
  "duration": 6600,
  "settings": [
    {"name":"showInternalStats", "value": "1" },
    {"name":"csvFileName", "value":"PlatformTesting"},
    {"name":"csvAppend", "value":"true"},
    {"name":"reconnectActive", "value": "1"},
    {"name": "checkSignedStateFromDisk", "value": "true"}
  ],
  "app": {
    "jar": "PlatformTestingApp.jar",
    "parameterList": ["FCMFCQ1K.json"]
  },
  "startSavedState": {
    "location": "s3://swirlds-regression/saved-states/FCQ-Batch-PTD/SetStakeInConfig/",
    "mainClass": "com.swirlds.demo.platform.PlatformTestingDemoMain",
    "swirldName": "123",
    "round": 4212,
    "restoreDb": true,
    "nodeIdentifier": "ALL_BUT_LAST"
  },
  "resultFiles": [
    "swirlds.log"
  ],
  "validator": [ "STATS", "RECONNECT"]
}
